conippets/__init__.py
conippets/config.py
conippets/datetime.py
conippets/json.py
conippets/jsonl.py
conippets/path.py
conippets/version.py
conippets-0.1.9.dist-info/LICENSE
conippets-0.1.9.dist-info/METADATA
conippets-0.1.9.dist-info/WHEEL
conippets-0.1.9.dist-info/top_level.txt
conippets-0.1.9.dist-info/RECORD
