Metadata-Version: 2.1
Name: conippets
Version: 0.1.9
Summary: conippets
Home-page: https://github.com/JiauZhang/conippets
Author: JiauZhang
Author-email: jiauzhang@163.com
License: MIT
Classifier: Intended Audience :: Developers
Classifier: License :: OSI Approved :: MIT License
Classifier: Programming Language :: Python :: 3.8
Requires-Python: >=3.8
License-File: LICENSE
